<mxfile host="Electron" modified="2023-10-23T14:23:08.428Z" agent="Mozilla/5.0 (X11; Linux x86_64) AppleWebKit/537.36 (KHTML, like Gecko) draw.io/22.0.3 Chrome/114.0.5735.289 Electron/25.8.4 Safari/537.36" etag="n0gi5qD_ZdCm6KtkKH6L" version="22.0.3" type="device">
  <diagram name="Page-1" id="10fhjVbzAiGWTrZmlpSp">
    <mxGraphModel dx="1520" dy="834" grid="1" gridSize="10" guides="1" tooltips="1" connect="1" arrows="1" fold="1" page="1" pageScale="1" pageWidth="827" pageHeight="1169" math="0" shadow="0">
      <root>
        <mxCell id="0" />
        <mxCell id="1" parent="0" />
        <mxCell id="dSW4Apbyi0pdc2GqMo_--14" style="rounded=0;orthogonalLoop=1;jettySize=auto;html=1;endArrow=none;endFill=0;" edge="1" parent="1" source="dSW4Apbyi0pdc2GqMo_--1" target="dSW4Apbyi0pdc2GqMo_--13">
          <mxGeometry relative="1" as="geometry" />
        </mxCell>
        <mxCell id="dSW4Apbyi0pdc2GqMo_--1" value="Cliente" style="shape=umlActor;verticalLabelPosition=bottom;verticalAlign=top;html=1;" vertex="1" parent="1">
          <mxGeometry x="130" y="190" width="30" height="60" as="geometry" />
        </mxCell>
        <mxCell id="dSW4Apbyi0pdc2GqMo_--11" style="rounded=0;orthogonalLoop=1;jettySize=auto;html=1;endArrow=none;endFill=0;" edge="1" parent="1" source="dSW4Apbyi0pdc2GqMo_--4" target="dSW4Apbyi0pdc2GqMo_--10">
          <mxGeometry relative="1" as="geometry" />
        </mxCell>
        <mxCell id="dSW4Apbyi0pdc2GqMo_--4" value="Utente non&lt;br&gt;Autenticato" style="shape=umlActor;verticalLabelPosition=bottom;verticalAlign=top;html=1;" vertex="1" parent="1">
          <mxGeometry x="130" y="360" width="30" height="60" as="geometry" />
        </mxCell>
        <mxCell id="dSW4Apbyi0pdc2GqMo_--19" style="edgeStyle=orthogonalEdgeStyle;rounded=0;orthogonalLoop=1;jettySize=auto;html=1;endArrow=block;endFill=0;" edge="1" parent="1" source="dSW4Apbyi0pdc2GqMo_--5" target="dSW4Apbyi0pdc2GqMo_--1">
          <mxGeometry relative="1" as="geometry" />
        </mxCell>
        <mxCell id="dSW4Apbyi0pdc2GqMo_--5" value="Dipendente" style="shape=umlActor;verticalLabelPosition=bottom;verticalAlign=top;html=1;" vertex="1" parent="1">
          <mxGeometry x="40" y="190" width="30" height="60" as="geometry" />
        </mxCell>
        <mxCell id="dSW4Apbyi0pdc2GqMo_--18" style="edgeStyle=orthogonalEdgeStyle;rounded=0;orthogonalLoop=1;jettySize=auto;html=1;endArrow=block;endFill=0;" edge="1" parent="1" source="dSW4Apbyi0pdc2GqMo_--6" target="dSW4Apbyi0pdc2GqMo_--5">
          <mxGeometry relative="1" as="geometry" />
        </mxCell>
        <mxCell id="dSW4Apbyi0pdc2GqMo_--6" value="Manager" style="shape=umlActor;verticalLabelPosition=bottom;verticalAlign=top;html=1;" vertex="1" parent="1">
          <mxGeometry x="-50" y="190" width="30" height="60" as="geometry" />
        </mxCell>
        <mxCell id="dSW4Apbyi0pdc2GqMo_--22" style="edgeStyle=orthogonalEdgeStyle;rounded=0;orthogonalLoop=1;jettySize=auto;html=1;" edge="1" parent="1" source="dSW4Apbyi0pdc2GqMo_--10" target="dSW4Apbyi0pdc2GqMo_--21">
          <mxGeometry relative="1" as="geometry" />
        </mxCell>
        <mxCell id="dSW4Apbyi0pdc2GqMo_--10" value="Vedere i&lt;br&gt;prodotti" style="ellipse;whiteSpace=wrap;html=1;" vertex="1" parent="1">
          <mxGeometry x="244" y="350" width="120" height="80" as="geometry" />
        </mxCell>
        <mxCell id="dSW4Apbyi0pdc2GqMo_--37" style="edgeStyle=orthogonalEdgeStyle;rounded=0;orthogonalLoop=1;jettySize=auto;html=1;" edge="1" parent="1" source="dSW4Apbyi0pdc2GqMo_--13" target="dSW4Apbyi0pdc2GqMo_--10">
          <mxGeometry relative="1" as="geometry" />
        </mxCell>
        <mxCell id="dSW4Apbyi0pdc2GqMo_--13" value="Aggiungere un prodotto&lt;br style=&quot;border-color: var(--border-color);&quot;&gt;al carrello" style="ellipse;whiteSpace=wrap;html=1;" vertex="1" parent="1">
          <mxGeometry x="244" y="180" width="120" height="80" as="geometry" />
        </mxCell>
        <mxCell id="dSW4Apbyi0pdc2GqMo_--16" style="edgeStyle=orthogonalEdgeStyle;rounded=0;orthogonalLoop=1;jettySize=auto;html=1;" edge="1" parent="1" source="dSW4Apbyi0pdc2GqMo_--15" target="dSW4Apbyi0pdc2GqMo_--13">
          <mxGeometry relative="1" as="geometry" />
        </mxCell>
        <mxCell id="dSW4Apbyi0pdc2GqMo_--29" style="edgeStyle=orthogonalEdgeStyle;rounded=0;orthogonalLoop=1;jettySize=auto;html=1;entryX=0.5;entryY=0;entryDx=0;entryDy=0;" edge="1" parent="1" source="dSW4Apbyi0pdc2GqMo_--15" target="dSW4Apbyi0pdc2GqMo_--25">
          <mxGeometry relative="1" as="geometry" />
        </mxCell>
        <mxCell id="dSW4Apbyi0pdc2GqMo_--34" style="edgeStyle=orthogonalEdgeStyle;rounded=0;orthogonalLoop=1;jettySize=auto;html=1;" edge="1" parent="1" source="dSW4Apbyi0pdc2GqMo_--15" target="dSW4Apbyi0pdc2GqMo_--33">
          <mxGeometry relative="1" as="geometry" />
        </mxCell>
        <mxCell id="dSW4Apbyi0pdc2GqMo_--15" value="Comprare&lt;br&gt;un prodotto" style="ellipse;whiteSpace=wrap;html=1;" vertex="1" parent="1">
          <mxGeometry x="464" y="180" width="120" height="80" as="geometry" />
        </mxCell>
        <mxCell id="dSW4Apbyi0pdc2GqMo_--17" value="&amp;lt;&amp;lt;extends&amp;gt;&amp;gt;" style="text;html=1;strokeColor=none;fillColor=none;align=center;verticalAlign=middle;whiteSpace=wrap;rounded=0;" vertex="1" parent="1">
          <mxGeometry x="384" y="190" width="60" height="30" as="geometry" />
        </mxCell>
        <mxCell id="dSW4Apbyi0pdc2GqMo_--23" style="edgeStyle=orthogonalEdgeStyle;rounded=0;orthogonalLoop=1;jettySize=auto;html=1;entryX=0;entryY=0.5;entryDx=0;entryDy=0;endArrow=none;endFill=0;" edge="1" parent="1" source="dSW4Apbyi0pdc2GqMo_--20" target="dSW4Apbyi0pdc2GqMo_--21">
          <mxGeometry relative="1" as="geometry" />
        </mxCell>
        <mxCell id="dSW4Apbyi0pdc2GqMo_--20" value="Database&lt;br&gt;Magazzino" style="shape=umlActor;verticalLabelPosition=bottom;verticalAlign=top;html=1;outlineConnect=0;" vertex="1" parent="1">
          <mxGeometry x="130" y="540" width="30" height="60" as="geometry" />
        </mxCell>
        <mxCell id="dSW4Apbyi0pdc2GqMo_--21" value="Comunicare i&lt;br&gt;prodotti" style="ellipse;whiteSpace=wrap;html=1;" vertex="1" parent="1">
          <mxGeometry x="244" y="530" width="120" height="80" as="geometry" />
        </mxCell>
        <mxCell id="dSW4Apbyi0pdc2GqMo_--24" value="&amp;lt;&amp;lt;include&amp;gt;&amp;gt;" style="text;html=1;strokeColor=none;fillColor=none;align=center;verticalAlign=middle;whiteSpace=wrap;rounded=0;" vertex="1" parent="1">
          <mxGeometry x="320" y="470" width="60" height="30" as="geometry" />
        </mxCell>
        <mxCell id="dSW4Apbyi0pdc2GqMo_--25" value="Effettuare il&lt;br&gt;pagamento" style="ellipse;whiteSpace=wrap;html=1;" vertex="1" parent="1">
          <mxGeometry x="464" y="350" width="120" height="80" as="geometry" />
        </mxCell>
        <mxCell id="dSW4Apbyi0pdc2GqMo_--27" style="edgeStyle=orthogonalEdgeStyle;rounded=0;orthogonalLoop=1;jettySize=auto;html=1;entryX=0.5;entryY=1;entryDx=0;entryDy=0;endArrow=none;endFill=0;" edge="1" parent="1" source="dSW4Apbyi0pdc2GqMo_--26" target="dSW4Apbyi0pdc2GqMo_--25">
          <mxGeometry relative="1" as="geometry" />
        </mxCell>
        <mxCell id="dSW4Apbyi0pdc2GqMo_--26" value="Paypal / Nexi" style="shape=umlActor;verticalLabelPosition=bottom;verticalAlign=top;html=1;" vertex="1" parent="1">
          <mxGeometry x="509" y="490" width="30" height="60" as="geometry" />
        </mxCell>
        <mxCell id="dSW4Apbyi0pdc2GqMo_--30" value="&amp;lt;&amp;lt;include&amp;gt;&amp;gt;" style="text;html=1;strokeColor=none;fillColor=none;align=center;verticalAlign=middle;whiteSpace=wrap;rounded=0;" vertex="1" parent="1">
          <mxGeometry x="539" y="280" width="60" height="30" as="geometry" />
        </mxCell>
        <mxCell id="dSW4Apbyi0pdc2GqMo_--36" style="edgeStyle=orthogonalEdgeStyle;rounded=0;orthogonalLoop=1;jettySize=auto;html=1;entryX=0.5;entryY=1;entryDx=0;entryDy=0;endArrow=none;endFill=0;" edge="1" parent="1" source="dSW4Apbyi0pdc2GqMo_--31" target="dSW4Apbyi0pdc2GqMo_--33">
          <mxGeometry relative="1" as="geometry" />
        </mxCell>
        <mxCell id="dSW4Apbyi0pdc2GqMo_--31" value="Database&lt;br&gt;Task" style="shape=umlActor;verticalLabelPosition=bottom;verticalAlign=top;html=1;" vertex="1" parent="1">
          <mxGeometry x="735" y="330" width="30" height="60" as="geometry" />
        </mxCell>
        <mxCell id="dSW4Apbyi0pdc2GqMo_--33" value="Creazione task&lt;br&gt;magazzino" style="ellipse;whiteSpace=wrap;html=1;" vertex="1" parent="1">
          <mxGeometry x="690" y="180" width="120" height="80" as="geometry" />
        </mxCell>
        <mxCell id="dSW4Apbyi0pdc2GqMo_--35" value="&amp;lt;&amp;lt;include&amp;gt;&amp;gt;" style="text;html=1;strokeColor=none;fillColor=none;align=center;verticalAlign=middle;whiteSpace=wrap;rounded=0;" vertex="1" parent="1">
          <mxGeometry x="610" y="190" width="60" height="30" as="geometry" />
        </mxCell>
        <mxCell id="dSW4Apbyi0pdc2GqMo_--38" value="&amp;lt;&amp;lt;extends&amp;gt;&amp;gt;" style="text;html=1;strokeColor=none;fillColor=none;align=center;verticalAlign=middle;whiteSpace=wrap;rounded=0;" vertex="1" parent="1">
          <mxGeometry x="324" y="290" width="60" height="30" as="geometry" />
        </mxCell>
      </root>
    </mxGraphModel>
  </diagram>
</mxfile>
